cerberuspackage/__init__.py
cerberuspackage/scrdf_cbr.py
cerberuspackage-0.0.3.dist-info/LICENSE
cerberuspackage-0.0.3.dist-info/METADATA
cerberuspackage-0.0.3.dist-info/WHEEL
cerberuspackage-0.0.3.dist-info/top_level.txt
cerberuspackage-0.0.3.dist-info/RECORD
