Metadata-Version: 2.1
Name: cerberuspackage
Version: 0.0.3
Summary: first version of package scrfd
Home-page: https://github.com/itachi176/cerberus-face-recognition
Author: HoangLM
Author-email: lhoang17062000@gmail.com
Classifier: Development Status :: 3 - Alpha
Classifier: Intended Audience :: Developers
Classifier: Topic :: Software Development :: Build Tools
Classifier: License :: OSI Approved :: MIT License
Classifier: Programming Language :: Python :: 3
Classifier: Programming Language :: Python :: 3.7
Classifier: Programming Language :: Python :: 3.8
Classifier: Programming Language :: Python :: 3.9
Classifier: Programming Language :: Python :: 3.10
Classifier: Programming Language :: Python :: 3 :: Only
License-File: LICENSE
Requires-Dist: numpy
Requires-Dist: onnx
Requires-Dist: onnxruntime
Requires-Dist: opencv-python
